lcprogramtools/__init__.py
lcprogramtools/module.py
lcprogramtools-1.0.0.dist-info/METADATA
lcprogramtools-1.0.0.dist-info/WHEEL
lcprogramtools-1.0.0.dist-info/entry_points.txt
lcprogramtools-1.0.0.dist-info/top_level.txt
lcprogramtools-1.0.0.dist-info/RECORD
