Metadata-Version: 2.1
Name: lcprogramtools
Version: 1.0.0
Summary: A demo Python package
Home-page: UNKNOWN
Author: Your Name
Author-email: your@email.com
License: UNKNOWN
Platform: UNKNOWN
Requires-Python: >=3.6
